chill_coffee_cash/__init__.py
chill_coffee_cash/main.py
coffee_cash_system-0.1.0.dist-info/LICENSE
coffee_cash_system-0.1.0.dist-info/METADATA
coffee_cash_system-0.1.0.dist-info/WHEEL
coffee_cash_system-0.1.0.dist-info/entry_points.txt
coffee_cash_system-0.1.0.dist-info/top_level.txt
coffee_cash_system-0.1.0.dist-info/RECORD
